mopidy_alsamixer/__init__.py
mopidy_alsamixer/ext.conf
mopidy_alsamixer/mixer.py
Mopidy_ALSAMixer-2.0.1.dist-info/LICENSE
Mopidy_ALSAMixer-2.0.1.dist-info/METADATA
Mopidy_ALSAMixer-2.0.1.dist-info/WHEEL
Mopidy_ALSAMixer-2.0.1.dist-info/entry_points.txt
Mopidy_ALSAMixer-2.0.1.dist-info/top_level.txt
Mopidy_ALSAMixer-2.0.1.dist-info/RECORD
